topsis/__init__.py
topsis/main.py
topsis_102217126-1.0.dist-info/METADATA
topsis_102217126-1.0.dist-info/WHEEL
topsis_102217126-1.0.dist-info/entry_points.txt
topsis_102217126-1.0.dist-info/top_level.txt
topsis_102217126-1.0.dist-info/RECORD
