Metadata-Version: 2.2
Name: topsis_102217126
Version: 1.0
Requires-Dist: numpy
Requires-Dist: pandas
Dynamic: description
Dynamic: description-content-type
Dynamic: requires-dist
